zzip/__init__.py
zzip-0.0.2.dist-info/WHEEL
zzip-0.0.2.dist-info/METADATA
zzip-0.0.2.dist-info/RECORD
